npy/__init__.py
npy/cli.py
npyproj-0.2.5.dist-info/METADATA
npyproj-0.2.5.dist-info/WHEEL
npyproj-0.2.5.dist-info/entry_points.txt
npyproj-0.2.5.dist-info/top_level.txt
npyproj-0.2.5.dist-info/RECORD
