Metadata-Version: 2.4
Name: npyproj
Version: 0.2.5
Summary: A lightweight Python project scaffolding CLI
Author: 778777266
Author-email: workmail2000@qq.com
Requires-Python: >=3.8
Dynamic: author
Dynamic: author-email
Dynamic: requires-python
Dynamic: summary
